dlib_validation_dest/__init__.py
dlib_validation_dest/validatingv2.py
dlib_validation_dest-2.0.0.dist-info/METADATA
dlib_validation_dest-2.0.0.dist-info/WHEEL
dlib_validation_dest-2.0.0.dist-info/top_level.txt
dlib_validation_dest-2.0.0.dist-info/RECORD
