Metadata-Version: 2.1
Name: dlib-validation-dest
Version: 2.0.0
Summary: library for trainning model ai
Home-page: UNKNOWN
Author: Jack Ma
Author-email: ma.jack@email.com
License: UNKNOWN
Platform: UNKNOWN
Classifier: Programming Language :: Python :: 3
Classifier: License :: OSI Approved :: MIT License
Classifier: Operating System :: OS Independent
Requires-Dist: dlib
Requires-Dist: joblib
Requires-Dist: numpy
Requires-Dist: opencv-python
Requires-Dist: python-dateutil
Requires-Dist: scikit-image
